securitytxt/__init__.py
securitytxt/core.py
securitytxt_parser-1.1.dist-info/LICENSE
securitytxt_parser-1.1.dist-info/METADATA
securitytxt_parser-1.1.dist-info/WHEEL
securitytxt_parser-1.1.dist-info/top_level.txt
securitytxt_parser-1.1.dist-info/RECORD
