Metadata-Version: 2.1
Name: securitytxt-parser
Version: 1.1
Summary: A Python project to parse security.txt file and URL.
Home-page: https://github.com/AethliosIK/securitytxt-parser
Author: Tom CHAMBARETAUD
Author-email: tom.chambaretaud@protonmail.com
License: MIT
Platform: UNKNOWN
Classifier: Programming Language :: Python
Classifier: Programming Language :: Python :: 3.7
Requires-Dist: requests
